qrh/__init__.py
qrh/qrh.py
qrh-1.0.dist-info/METADATA
qrh-1.0.dist-info/WHEEL
qrh-1.0.dist-info/entry_points.txt
qrh-1.0.dist-info/top_level.txt
qrh-1.0.dist-info/RECORD
