Metadata-Version: 2.4
Name: QRH
Version: 1.0
Summary: Advanced QR Code Generator Tool (QRH)
Author: Babar Ali Jamali
Author-email: babar995@gmail.com
Requires-Python: >=3.6
Requires-Dist: qrcode
Requires-Dist: fpdf
Dynamic: author
Dynamic: author-email
Dynamic: requires-dist
Dynamic: requires-python
Dynamic: summary
